addition2integers/__init__.py
addition2integers/math_utils.py
addition2integers-0.1.0.dist-info/LICENSE.txt
addition2integers-0.1.0.dist-info/METADATA
addition2integers-0.1.0.dist-info/WHEEL
addition2integers-0.1.0.dist-info/top_level.txt
addition2integers-0.1.0.dist-info/RECORD
