Metadata-Version: 2.1
Name: addition2integers
Version: 0.1.0
Summary: A utility package for math and string operations
Home-page: https://github.com/MuhammadTalha-crypto/sum
Author: Talha
Author-email: your.email@example.com
Classifier: Programming Language :: Python :: 3
Classifier: License :: OSI Approved :: MIT License
Classifier: Operating System :: OS Independent
Requires-Python: >=3.6
License-File: LICENSE.txt
